conflux_segmentation/__init__.py
conflux_segmentation/defaults.py
conflux_segmentation/onnx.py
conflux_segmentation/py.typed
conflux_segmentation/segmentation_result.py
conflux_segmentation/segmenter.py
conflux_segmentation/tile_segmenter.py
conflux_segmentation/torch.py
conflux_segmentation/transforms.py
conflux_segmentation/types.py
conflux_segmentation/utils.py
conflux_segmentation-0.5.0.dist-info/METADATA
conflux_segmentation-0.5.0.dist-info/WHEEL
conflux_segmentation-0.5.0.dist-info/licenses/LICENSE
conflux_segmentation-0.5.0.dist-info/RECORD
