Metadata-Version: 2.4
Name: conflux-segmentation
Version: 0.5.0
Summary: Tile-based inference for segmentation of large images.
License: Apache-2.0
License-File: LICENSE
Author: Conflux
Maintainer: Conflux
Requires-Python: >=3.10,<4.0
Classifier: License :: OSI Approved :: Apache Software License
Classifier: Programming Language :: Python :: 3
Classifier: Programming Language :: Python :: 3.10
Classifier: Programming Language :: Python :: 3.11
Classifier: Programming Language :: Python :: 3.12
Classifier: Programming Language :: Python :: 3.13
Classifier: Programming Language :: Python :: 3.14
Provides-Extra: onnx
Provides-Extra: torch
Requires-Dist: numpy (>=1,<3)
Requires-Dist: onnxruntime (>=1,<2) ; extra == "onnx"
Requires-Dist: torch (>=2,<3) ; extra == "torch"
Project-URL: Bug Tracker, https://github.com/conflux-xyz/conflux-segmentation/issues
Project-URL: Repository, https://github.com/conflux-xyz/conflux-segmentation
